Workbook

Sheet README
A1: Tallyrow prioritisation workbook
A2: Product Management Models & Measurements · Prioritisation models
A4: Tallyrow is a fictional invoicing and payments app. Every number in this workbook is invented for teaching.
A6: Tabs
A7: RICE · Tallyrow: the quarter's eight backlog items, scored with honest inputs and a live ranked view.
A8: RICE · your backlog: the same sheet, blank. Fill the grey input columns; the score, rank and ranked view update.
A9: Weighted · Tallyrow: four criteria and weights agreed before scoring, the eight items scored 1-5, a live ranked view.
A10: Weighted · your backlog: blank. Agree the criteria, weights and anchors, and date them, before anyone scores.
A11: ICE · experiments: small, cheap tests scored Impact × Confidence × Ease, plus blank rows for your own.
A12: MoSCoW · Tallyrow: the quarter fitted to 10 person-months. Musts at 60%, Should 20%, Could 20%, five Won'ts.
A13: MoSCoW · your release: blank. Set your capacity, place every item, keep the Musts at or under about 60%.
A14: CD3 · Tallyrow: cost of delay ÷ duration, ranked; plus the dates-first block (e-invoicing starts by week 3) and smart reminders' range.
... A22: Sources: RICE, Sean McBride, Intercom, 5 Jan 2018. ICE, credited to Sean Ellis. MoSCoW, Dai Clegg (1994), DSDM / Agile Business Consortium. CD3, Black Swan Farming. WSJF, SAFe (Scaled Agile Framework).

Sheet RICE · Tallyrow
A1: RICE · Tallyrow backlog (honest inputs)
A2: One unit, one impact anchor, one evidence rule. Change any grey input and watch the ranked view.
A4: # | B4: Item | C4: Squad | D4: Reach | E4: Reach unit | F4: Unit check | G4: Impact | H4: Confidence | I4: Effort (p-m) | J4: RICE score | K4: Rank | L4: Evidence (why this confidence?) | N4: Rank | O4: Ranked view | P4: Score
A5: 1 | B5: Payment link | C5: Get Paid | D5: 12000 | E5: businesses / quarter | F5: =IF(E5="","",IF(E5=Anchors!$B$4,"✓","✗ unit")) | G5: 2 | H5: 0.8 | I5: 2 | J5: =IF(COUNT(D5,G5,H5,I5)<4,"",D5*G5*H5/I5) | K5: =IF(J5="","",RANK(J5,$J$5:$J$12)+COUNTIF($J$5:J5,J5)-1) | L5: Reach: support-ticket and usage data. Impact: no measured lift yet. Effort: engineering estimate. | N5: 1 | O5: =IFERROR(INDEX($B$5:$B$12,MATCH(N5,$K$5:$K$12,0)),"") | P5: =IFERROR(INDEX($J$5:$J$12,MATCH(N5,$K$5:$K$12,0)),"")
A6: 2 | B6: Smart reminders | C6: Get Paid | D6: 24000 | E6: businesses / quarter | F6: =IF(E6="","",IF(E6=Anchors!$B$4,"✓","✗ unit")) | G6: 2 | H6: 0.5 | I6: 4 | J6: =IF(COUNT(D6,G6,H6,I6)<4,"",D6*G6*H6/I6) | K6: =IF(J6="","",RANK(J6,$J$5:$J$12)+COUNTIF($J$5:J6,J6)-1) | L6: Timing model not built. Impact borrowed from a competitor's demo. Reach assumes every reminder sender adopts it. | N6: 2 | O6: =IFERROR(INDEX($B$5:$B$12,MATCH(N6,$K$5:$K$12,0)),"") | P6: =IFERROR(INDEX($J$5:$J$12,MATCH(N6,$K$5:$K$12,0)),"")
A7: 3 | B7: Recurring invoices | C7: Invoicing | D7: 8000 | E7: businesses / quarter | F7: =IF(E7="","",IF(E7=Anchors!$B$4,"✓","✗ unit")) | G7: 1 | H7: 1 | I7: 2 | J7: =IF(COUNT(D7,G7,H7,I7)<4,"",D7*G7*H7/I7) | K7: =IF(J7="","",RANK(J7,$J$5:$J$12)+COUNTIF($J$5:J7,J7)-1) | L7: Reach: account data. Impact: top request on the feedback board. Effort: engineering estimate. | N7: 3 | O7: =IFERROR(INDEX($B$5:$B$12,MATCH(N7,$K$5:$K$12,0)),"") | P7: =IFERROR(INDEX($J$5:$J$12,MATCH(N7,$K$5:$K$12,0)),"")
A8: 4 | B8: E-invoicing | C8: Platform & Compliance | D8: 3000 | E8: businesses / quarter | F8: =IF(E8="","",IF(E8=Anchors!$B$4,"✓","✗ unit")) | G8: 3 | H8: 0.8 | I8: 4 | J8: =IF(COUNT(D8,G8,H8,I8)<4,"",D8*G8*H8/I8) | K8: =IF(J8="","",RANK(J8,$J$5:$J$12)+COUNTIF($J$5:J8,J8)-1) | L8: Reach: businesses in the one market. Impact: legally required there. Effort depends on the regulator's spec. | N8: 4 | O8: =IFERROR(INDEX($B$5:$B$12,MATCH(N8,$K$5:$K$12,0)),"") | P8: =IFERROR(INDEX($J$5:$J$12,MATCH(N8,$K$5:$K$12,0)),"")
A9: 5 | B9: Multi-currency | C9: Invoicing | D9: 1500 | E9: businesses / quarter | F9: =IF(E9="","",IF(E9=Anchors!$B$4,"✓","✗ unit")) | G9: 2 | H9: 0.8 | I9: 2 | J9: =IF(COUNT(D9,G9,H9,I9)<4,"",D9*G9*H9/I9) | K9: =IF(J9="","",RANK(J9,$J$5:$J$12)+COUNTIF($J$5:J9,J9)-1) | L9: Reach: one large agency deal plus a few accounts. Impact: sales input. Effort: engineering estimate. | N9: 5 | O9: =IFERROR(INDEX($B$5:$B$12,MATCH(N9,$K$5:$K$12,0)),"") | P9: =IFERROR(INDEX($J$5:$J$12,MATCH(N9,$K$5:$K$12,0)),"")
A10: 6 | B10: Client portal | C10: Invoicing | D10: 15000 | E10: businesses / quarter | F10: =IF(E10="","",IF(E10=Anchors!$B$4,"✓","✗ unit")) | G10: 1 | H10: 0.8 | I10: 6 | J10: =IF(COUNT(D10,G10,H10,I10)<4,"",D10*G10*H10/I10) | K10: =IF(J10="","",RANK(J10,$J$5:$J$12)+COUNTIF($J$5:J10,J10)-1) | L10: Impact anchored to invoices paid on time: some lift, so medium. Effort: design and engineering estimate. | N10: 6 | O10: =IFERROR(INDEX($B$5:$B$12,MATCH(N10,$K$5:$K$12,0)),"") | P10: =IFERROR(INDEX($J$5:$J$12,MATCH(N10,$K$5:$K$12,0)),"")
A11: 7 | B11: Late-fee automation | C11: Get Paid | D11: 6000 | E11: businesses / quarter | F11: =IF(E11="","",IF(E11=Anchors!$B$4,"✓","✗ unit")) | G11: 1 | H11: 0.8 | I11: 2 | J11: =IF(COUNT(D11,G11,H11,I11)<4,"",D11*G11*H11/I11) | K11: =IF(J11="","",RANK(J11,$J$5:$J$12)+COUNTIF($J$5:J11,J11)-1) | L11: Reach: accounts with overdue invoices. Not scored by RICE: risk to clients' relationships (guardrail). | N11: 7 | O11: =IFERROR(INDEX($B$5:$B$12,MATCH(N11,$K$5:$K$12,0)),"") | P11: =IFERROR(INDEX($J$5:$J$12,MATCH(N11,$K$5:$K$12,0)),"")
A12: 8 | B12: Receipt capture | C12: Invoicing | D12: 10000 | E12: businesses / quarter | F12: =IF(E12="","",IF(E12=Anchors!$B$4,"✓","✗ unit")) | G12: 0.5 | H12: 0.8 | I12: 4 | J12: =IF(COUNT(D12,G12,H12,I12)<4,"",D12*G12*H12/I12) | K12: =IF(J12="","",RANK(J12,$J$5:$J$12)+COUNTIF($J$5:J12,J12)-1) | L12: Reach: user survey. Impact: adjacent to the core job, so low. | N12: 8 | O12: =IFERROR(INDEX($B$5:$B$12,MATCH(N12,$K$5:$K$12,0)),"") | P12: =IFERROR(INDEX($J$5:$J$12,MATCH(N12,$K$5:$K$12,0)),"")
B14: Formula: RICE = (Reach × Impact × Confidence) ÷ Effort. Scales and rules: see the Anchors tab.
B15: Every Tallyrow number is invented for teaching.

Sheet RICE · your backlog
A1: RICE · your backlog
A2: Agree the Anchors tab first. Fill Item to Effort; write the evidence for every confidence value.
A4: # | B4: Item | C4: Squad | D4: Reach | E4: Reach unit | F4: Unit check | G4: Impact | H4: Confidence | I4: Effort (p-m) | J4: RICE score | K4: Rank | L4: Evidence (why this confidence?) | N4: Rank | O4: Ranked view | P4: Score
A5: 1 | F5: =IF(E5="","",IF(E5=Anchors!$B$4,"✓","✗ unit")) | J5: =IF(COUNT(D5,G5,H5,I5)<4,"",D5*G5*H5/I5) | K5: =IF(J5="","",RANK(J5,$J$5:$J$19)+COUNTIF($J$5:J5,J5)-1) | N5: 1 | O5: =IFERROR(INDEX($B$5:$B$19,MATCH(N5,$K$5:$K$19,0)),"") | P5: =IFERROR(INDEX($J$5:$J$19,MATCH(N5,$K$5:$K$19,0)),"")
A6: 2 | F6: =IF(E6="","",IF(E6=Anchors!$B$4,"✓","✗ unit")) | J6: =IF(COUNT(D6,G6,H6,I6)<4,"",D6*G6*H6/I6) | K6: =IF(J6="","",RANK(J6,$J$5:$J$19)+COUNTIF($J$5:J6,J6)-1) | N6: 2 | O6: =IFERROR(INDEX($B$5:$B$19,MATCH(N6,$K$5:$K$19,0)),"") | P6: =IFERROR(INDEX($J$5:$J$19,MATCH(N6,$K$5:$K$19,0)),"")
A7: 3 | F7: =IF(E7="","",IF(E7=Anchors!$B$4,"✓","✗ unit")) | J7: =IF(COUNT(D7,G7,H7,I7)<4,"",D7*G7*H7/I7) | K7: =IF(J7="","",RANK(J7,$J$5:$J$19)+COUNTIF($J$5:J7,J7)-1) | N7: 3 | O7: =IFERROR(INDEX($B$5:$B$19,MATCH(N7,$K$5:$K$19,0)),"") | P7: =IFERROR(INDEX($J$5:$J$19,MATCH(N7,$K$5:$K$19,0)),"")
A8: 4 | F8: =IF(E8="","",IF(E8=Anchors!$B$4,"✓","✗ unit")) | J8: =IF(COUNT(D8,G8,H8,I8)<4,"",D8*G8*H8/I8) | K8: =IF(J8="","",RANK(J8,$J$5:$J$19)+COUNTIF($J$5:J8,J8)-1) | N8: 4 | O8: =IFERROR(INDEX($B$5:$B$19,MATCH(N8,$K$5:$K$19,0)),"") | P8: =IFERROR(INDEX($J$5:$J$19,MATCH(N8,$K$5:$K$19,0)),"")
A9: 5 | F9: =IF(E9="","",IF(E9=Anchors!$B$4,"✓","✗ unit")) | J9: =IF(COUNT(D9,G9,H9,I9)<4,"",D9*G9*H9/I9) | K9: =IF(J9="","",RANK(J9,$J$5:$J$19)+COUNTIF($J$5:J9,J9)-1) | N9: 5 | O9: =IFERROR(INDEX($B$5:$B$19,MATCH(N9,$K$5:$K$19,0)),"") | P9: =IFERROR(INDEX($J$5:$J$19,MATCH(N9,$K$5:$K$19,0)),"")
A10: 6 | F10: =IF(E10="","",IF(E10=Anchors!$B$4,"✓","✗ unit")) | J10: =IF(COUNT(D10,G10,H10,I10)<4,"",D10*G10*H10/I10) | K10: =IF(J10="","",RANK(J10,$J$5:$J$19)+COUNTIF($J$5:J10,J10)-1) | N10: 6 | O10: =IFERROR(INDEX($B$5:$B$19,MATCH(N10,$K$5:$K$19,0)),"") | P10: =IFERROR(INDEX($J$5:$J$19,MATCH(N10,$K$5:$K$19,0)),"")
A11: 7 | F11: =IF(E11="","",IF(E11=Anchors!$B$4,"✓","✗ unit")) | J11: =IF(COUNT(D11,G11,H11,I11)<4,"",D11*G11*H11/I11) | K11: =IF(J11="","",RANK(J11,$J$5:$J$19)+COUNTIF($J$5:J11,J11)-1) | N11: 7 | O11: =IFERROR(INDEX($B$5:$B$19,MATCH(N11,$K$5:$K$19,0)),"") | P11: =IFERROR(INDEX($J$5:$J$19,MATCH(N11,$K$5:$K$19,0)),"")
A12: 8 | F12: =IF(E12="","",IF(E12=Anchors!$B$4,"✓","✗ unit")) | J12: =IF(COUNT(D12,G12,H12,I12)<4,"",D12*G12*H12/I12) | K12: =IF(J12="","",RANK(J12,$J$5:$J$19)+COUNTIF($J$5:J12,J12)-1) | N12: 8 | O12: =IFERROR(INDEX($B$5:$B$19,MATCH(N12,$K$5:$K$19,0)),"") | P12: =IFERROR(INDEX($J$5:$J$19,MATCH(N12,$K$5:$K$19,0)),"")
A13: 9 | F13: =IF(E13="","",IF(E13=Anchors!$B$4,"✓","✗ unit")) | J13: =IF(COUNT(D13,G13,H13,I13)<4,"",D13*G13*H13/I13) | K13: =IF(J13="","",RANK(J13,$J$5:$J$19)+COUNTIF($J$5:J13,J13)-1) | N13: 9 | O13: =IFERROR(INDEX($B$5:$B$19,MATCH(N13,$K$5:$K$19,0)),"") | P13: =IFERROR(INDEX($J$5:$J$19,MATCH(N13,$K$5:$K$19,0)),"")
A14: 10 | F14: =IF(E14="","",IF(E14=Anchors!$B$4,"✓","✗ unit")) | J14: =IF(COUNT(D14,G14,H14,I14)<4,"",D14*G14*H14/I14) | K14: =IF(J14="","",RANK(J14,$J$5:$J$19)+COUNTIF($J$5:J14,J14)-1) | N14: 10 | O14: =IFERROR(INDEX($B$5:$B$19,MATCH(N14,$K$5:$K$19,0)),"") | P14: =IFERROR(INDEX($J$5:$J$19,MATCH(N14,$K$5:$K$19,0)),"")
A15: 11 | F15: =IF(E15="","",IF(E15=Anchors!$B$4,"✓","✗ unit")) | J15: =IF(COUNT(D15,G15,H15,I15)<4,"",D15*G15*H15/I15) | K15: =IF(J15="","",RANK(J15,$J$5:$J$19)+COUNTIF($J$5:J15,J15)-1) | N15: 11 | O15: =IFERROR(INDEX($B$5:$B$19,MATCH(N15,$K$5:$K$19,0)),"") | P15: =IFERROR(INDEX($J$5:$J$19,MATCH(N15,$K$5:$K$19,0)),"")
A16: 12 | F16: =IF(E16="","",IF(E16=Anchors!$B$4,"✓","✗ unit")) | J16: =IF(COUNT(D16,G16,H16,I16)<4,"",D16*G16*H16/I16) | K16: =IF(J16="","",RANK(J16,$J$5:$J$19)+COUNTIF($J$5:J16,J16)-1) | N16: 12 | O16: =IFERROR(INDEX($B$5:$B$19,MATCH(N16,$K$5:$K$19,0)),"") | P16: =IFERROR(INDEX($J$5:$J$19,MATCH(N16,$K$5:$K$19,0)),"")
... A19: 15 | F19: =IF(E19="","",IF(E19=Anchors!$B$4,"✓","✗ unit")) | J19: =IF(COUNT(D19,G19,H19,I19)<4,"",D19*G19*H19/I19) | K19: =IF(J19="","",RANK(J19,$J$5:$J$19)+COUNTIF($J$5:J19,J19)-1) | N19: 15 | O19: =IFERROR(INDEX($B$5:$B$19,MATCH(N19,$K$5:$K$19,0)),"") | P19: =IFERROR(INDEX($J$5:$J$19,MATCH(N19,$K$5:$K$19,0)),"")
B21: Formula: RICE = (Reach × Impact × Confidence) ÷ Effort. Scales and rules: see the Anchors tab.
B22: Every Tallyrow number is invented for teaching.

Sheet Weighted · Tallyrow
A1: Weighted scoring · Tallyrow backlog
A2: Criteria and weights agreed with Maya and Tomás before anyone scored. Change a weight and watch the ranked view.
B4: Criterion | C4: Lift to invoices paid on time | D4: Revenue and retention | E4: Strategic or compliance need | F4: Ease | G4: Weights total
B5: Weight | C5: 0.4 | D5: 0.25 | E5: 0.15 | F5: 0.2 | G5: =IF(COUNT(C5:F5)=0,"",IF(ROUND(SUM(C5:F5),4)=1,"✓ 100%","✗ "&TEXT(SUM(C5:F5),"0%")))
B6: Agreed by / date | C6: Maya (CEO), Tomás (Finance lead) | F6: Planning day 1, before scoring
A8: # | B8: Item | C8: Lift (1-5) | D8: Revenue (1-5) | E8: Strategic (1-5) | F8: Ease (1-5) | G8: Weighted total | H8: Rank | K8: Rank | L8: Ranked view | M8: Total
A9: 1 | B9: Payment link | C9: 5 | D9: 4 | E9: 3 | F9: 4 | G9: =IF(COUNT(C9:F9)<4,"",SUMPRODUCT($C$5:$F$5,C9:F9)) | H9: =IF(G9="","",COUNTIF($G$9:$G$16,">"&(G9+0.005))+1) | I9: =IF(H9="","",H9+COUNTIF($H$9:H9,H9)-1) | K9: =IFERROR(INDEX($H$9:$H$16,MATCH(1,$I$9:$I$16,0)),"") | L9: =IFERROR(INDEX($B$9:$B$16,MATCH(1,$I$9:$I$16,0)),"") | M9: =IFERROR(INDEX($G$9:$G$16,MATCH(1,$I$9:$I$16,0)),"")
A10: 2 | B10: Smart reminders | C10: 4 | D10: 3 | E10: 4 | F10: 2 | G10: =IF(COUNT(C10:F10)<4,"",SUMPRODUCT($C$5:$F$5,C10:F10)) | H10: =IF(G10="","",COUNTIF($G$9:$G$16,">"&(G10+0.005))+1) | I10: =IF(H10="","",H10+COUNTIF($H$9:H10,H10)-1) | K10: =IFERROR(INDEX($H$9:$H$16,MATCH(2,$I$9:$I$16,0)),"") | L10: =IFERROR(INDEX($B$9:$B$16,MATCH(2,$I$9:$I$16,0)),"") | M10: =IFERROR(INDEX($G$9:$G$16,MATCH(2,$I$9:$I$16,0)),"")
A11: 3 | B11: Recurring invoices | C11: 3 | D11: 4 | E11: 2 | F11: 4 | G11: =IF(COUNT(C11:F11)<4,"",SUMPRODUCT($C$5:$F$5,C11:F11)) | H11: =IF(G11="","",COUNTIF($G$9:$G$16,">"&(G11+0.005))+1) | I11: =IF(H11="","",H11+COUNTIF($H$9:H11,H11)-1) | K11: =IFERROR(INDEX($H$9:$H$16,MATCH(3,$I$9:$I$16,0)),"") | L11: =IFERROR(INDEX($B$9:$B$16,MATCH(3,$I$9:$I$16,0)),"") | M11: =IFERROR(INDEX($G$9:$G$16,MATCH(3,$I$9:$I$16,0)),"")
A12: 4 | B12: E-invoicing | C12: 1 | D12: 3 | E12: 5 | F12: 2 | G12: =IF(COUNT(C12:F12)<4,"",SUMPRODUCT($C$5:$F$5,C12:F12)) | H12: =IF(G12="","",COUNTIF($G$9:$G$16,">"&(G12+0.005))+1) | I12: =IF(H12="","",H12+COUNTIF($H$9:H12,H12)-1) | K12: =IFERROR(INDEX($H$9:$H$16,MATCH(4,$I$9:$I$16,0)),"") | L12: =IFERROR(INDEX($B$9:$B$16,MATCH(4,$I$9:$I$16,0)),"") | M12: =IFERROR(INDEX($G$9:$G$16,MATCH(4,$I$9:$I$16,0)),"")
A13: 5 | B13: Multi-currency | C13: 1 | D13: 3 | E13: 2 | F13: 4 | G13: =IF(COUNT(C13:F13)<4,"",SUMPRODUCT($C$5:$F$5,C13:F13)) | H13: =IF(G13="","",COUNTIF($G$9:$G$16,">"&(G13+0.005))+1) | I13: =IF(H13="","",H13+COUNTIF($H$9:H13,H13)-1) | K13: =IFERROR(INDEX($H$9:$H$16,MATCH(5,$I$9:$I$16,0)),"") | L13: =IFERROR(INDEX($B$9:$B$16,MATCH(5,$I$9:$I$16,0)),"") | M13: =IFERROR(INDEX($G$9:$G$16,MATCH(5,$I$9:$I$16,0)),"")
A14: 6 | B14: Client portal | C14: 3 | D14: 2 | E14: 2 | F14: 1 | G14: =IF(COUNT(C14:F14)<4,"",SUMPRODUCT($C$5:$F$5,C14:F14)) | H14: =IF(G14="","",COUNTIF($G$9:$G$16,">"&(G14+0.005))+1) | I14: =IF(H14="","",H14+COUNTIF($H$9:H14,H14)-1) | K14: =IFERROR(INDEX($H$9:$H$16,MATCH(6,$I$9:$I$16,0)),"") | L14: =IFERROR(INDEX($B$9:$B$16,MATCH(6,$I$9:$I$16,0)),"") | M14: =IFERROR(INDEX($G$9:$G$16,MATCH(6,$I$9:$I$16,0)),"")
A15: 7 | B15: Late-fee automation | C15: 2 | D15: 4 | E15: 1 | F15: 4 | G15: =IF(COUNT(C15:F15)<4,"",SUMPRODUCT($C$5:$F$5,C15:F15)) | H15: =IF(G15="","",COUNTIF($G$9:$G$16,">"&(G15+0.005))+1) | I15: =IF(H15="","",H15+COUNTIF($H$9:H15,H15)-1) | K15: =IFERROR(INDEX($H$9:$H$16,MATCH(7,$I$9:$I$16,0)),"") | L15: =IFERROR(INDEX($B$9:$B$16,MATCH(7,$I$9:$I$16,0)),"") | M15: =IFERROR(INDEX($G$9:$G$16,MATCH(7,$I$9:$I$16,0)),"")
A16: 8 | B16: Receipt capture | C16: 1 | D16: 2 | E16: 1 | F16: 2 | G16: =IF(COUNT(C16:F16)<4,"",SUMPRODUCT($C$5:$F$5,C16:F16)) | H16: =IF(G16="","",COUNTIF($G$9:$G$16,">"&(G16+0.005))+1) | I16: =IF(H16="","",H16+COUNTIF($H$9:H16,H16)-1) | K16: =IFERROR(INDEX($H$9:$H$16,MATCH(8,$I$9:$I$16,0)),"") | L16: =IFERROR(INDEX($B$9:$B$16,MATCH(8,$I$9:$I$16,0)),"") | M16: =IFERROR(INDEX($G$9:$G$16,MATCH(8,$I$9:$I$16,0)),"")
B18: Criteria anchors: agree these with the weights, BEFORE anyone scores
B19: Criterion | C19: 1 means | F19: 5 means
B20: Lift | C20: Barely moves invoices paid on time, or reaches few customers | F20: Large lift for most of the customer base
B21: Revenue | C21: No effect on revenue or on customers staying | F21: Clear new revenue, or a top reason customers stay
B22: Strategic | C22: Nice to have | F22: Legally required, or a bet the company has stated
B23: Ease | C23: 6 or more person-months (4 = about 2, 2 = about 4) | F23: Well under 1 person-month
B25: Weighted total = SUMPRODUCT(weights, scores). Equal totals share a rank.
B26: Weights and anchors are agreed, written down and dated before scoring. Change them after scoring and the ranking is chosen first, justified second.
B27: Like RICE, this tab has no column for time: deadlines are priced by Cost of Delay.
B28: Every Tallyrow number is invented for teaching.

Sheet Weighted · your backlog
A1: Weighted scoring · your backlog
A2: Step 1: criteria, weights (total 100%) and anchors, agreed and dated. Step 2: only then, score each item 1-5.
B4: Criterion | C4: Lift to invoices paid on time | D4: Revenue and retention | E4: Strategic or compliance need | F4: Ease | G4: Weights total
B5: Weight | G5: =IF(COUNT(C5:F5)=0,"",IF(ROUND(SUM(C5:F5),4)=1,"✓ 100%","✗ "&TEXT(SUM(C5:F5),"0%")))
B6: Agreed by / date
A8: # | B8: Item | C8: Lift (1-5) | D8: Revenue (1-5) | E8: Strategic (1-5) | F8: Ease (1-5) | G8: Weighted total | H8: Rank | K8: Rank | L8: Ranked view | M8: Total
A9: 1 | G9: =IF(COUNT(C9:F9)<4,"",SUMPRODUCT($C$5:$F$5,C9:F9)) | H9: =IF(G9="","",COUNTIF($G$9:$G$23,">"&(G9+0.005))+1) | I9: =IF(H9="","",H9+COUNTIF($H$9:H9,H9)-1) | K9: =IFERROR(INDEX($H$9:$H$23,MATCH(1,$I$9:$I$23,0)),"") | L9: =IFERROR(INDEX($B$9:$B$23,MATCH(1,$I$9:$I$23,0)),"") | M9: =IFERROR(INDEX($G$9:$G$23,MATCH(1,$I$9:$I$23,0)),"")
A10: 2 | G10: =IF(COUNT(C10:F10)<4,"",SUMPRODUCT($C$5:$F$5,C10:F10)) | H10: =IF(G10="","",COUNTIF($G$9:$G$23,">"&(G10+0.005))+1) | I10: =IF(H10="","",H10+COUNTIF($H$9:H10,H10)-1) | K10: =IFERROR(INDEX($H$9:$H$23,MATCH(2,$I$9:$I$23,0)),"") | L10: =IFERROR(INDEX($B$9:$B$23,MATCH(2,$I$9:$I$23,0)),"") | M10: =IFERROR(INDEX($G$9:$G$23,MATCH(2,$I$9:$I$23,0)),"")
A11: 3 | G11: =IF(COUNT(C11:F11)<4,"",SUMPRODUCT($C$5:$F$5,C11:F11)) | H11: =IF(G11="","",COUNTIF($G$9:$G$23,">"&(G11+0.005))+1) | I11: =IF(H11="","",H11+COUNTIF($H$9:H11,H11)-1) | K11: =IFERROR(INDEX($H$9:$H$23,MATCH(3,$I$9:$I$23,0)),"") | L11: =IFERROR(INDEX($B$9:$B$23,MATCH(3,$I$9:$I$23,0)),"") | M11: =IFERROR(INDEX($G$9:$G$23,MATCH(3,$I$9:$I$23,0)),"")
A12: 4 | G12: =IF(COUNT(C12:F12)<4,"",SUMPRODUCT($C$5:$F$5,C12:F12)) | H12: =IF(G12="","",COUNTIF($G$9:$G$23,">"&(G12+0.005))+1) | I12: =IF(H12="","",H12+COUNTIF($H$9:H12,H12)-1) | K12: =IFERROR(INDEX($H$9:$H$23,MATCH(4,$I$9:$I$23,0)),"") | L12: =IFERROR(INDEX($B$9:$B$23,MATCH(4,$I$9:$I$23,0)),"") | M12: =IFERROR(INDEX($G$9:$G$23,MATCH(4,$I$9:$I$23,0)),"")
A13: 5 | G13: =IF(COUNT(C13:F13)<4,"",SUMPRODUCT($C$5:$F$5,C13:F13)) | H13: =IF(G13="","",COUNTIF($G$9:$G$23,">"&(G13+0.005))+1) | I13: =IF(H13="","",H13+COUNTIF($H$9:H13,H13)-1) | K13: =IFERROR(INDEX($H$9:$H$23,MATCH(5,$I$9:$I$23,0)),"") | L13: =IFERROR(INDEX($B$9:$B$23,MATCH(5,$I$9:$I$23,0)),"") | M13: =IFERROR(INDEX($G$9:$G$23,MATCH(5,$I$9:$I$23,0)),"")
A14: 6 | G14: =IF(COUNT(C14:F14)<4,"",SUMPRODUCT($C$5:$F$5,C14:F14)) | H14: =IF(G14="","",COUNTIF($G$9:$G$23,">"&(G14+0.005))+1) | I14: =IF(H14="","",H14+COUNTIF($H$9:H14,H14)-1) | K14: =IFERROR(INDEX($H$9:$H$23,MATCH(6,$I$9:$I$23,0)),"") | L14: =IFERROR(INDEX($B$9:$B$23,MATCH(6,$I$9:$I$23,0)),"") | M14: =IFERROR(INDEX($G$9:$G$23,MATCH(6,$I$9:$I$23,0)),"")
A15: 7 | G15: =IF(COUNT(C15:F15)<4,"",SUMPRODUCT($C$5:$F$5,C15:F15)) | H15: =IF(G15="","",COUNTIF($G$9:$G$23,">"&(G15+0.005))+1) | I15: =IF(H15="","",H15+COUNTIF($H$9:H15,H15)-1) | K15: =IFERROR(INDEX($H$9:$H$23,MATCH(7,$I$9:$I$23,0)),"") | L15: =IFERROR(INDEX($B$9:$B$23,MATCH(7,$I$9:$I$23,0)),"") | M15: =IFERROR(INDEX($G$9:$G$23,MATCH(7,$I$9:$I$23,0)),"")
A16: 8 | G16: =IF(COUNT(C16:F16)<4,"",SUMPRODUCT($C$5:$F$5,C16:F16)) | H16: =IF(G16="","",COUNTIF($G$9:$G$23,">"&(G16+0.005))+1) | I16: =IF(H16="","",H16+COUNTIF($H$9:H16,H16)-1) | K16: =IFERROR(INDEX($H$9:$H$23,MATCH(8,$I$9:$I$23,0)),"") | L16: =IFERROR(INDEX($B$9:$B$23,MATCH(8,$I$9:$I$23,0)),"") | M16: =IFERROR(INDEX($G$9:$G$23,MATCH(8,$I$9:$I$23,0)),"")
A17: 9 | G17: =IF(COUNT(C17:F17)<4,"",SUMPRODUCT($C$5:$F$5,C17:F17)) | H17: =IF(G17="","",COUNTIF($G$9:$G$23,">"&(G17+0.005))+1) | I17: =IF(H17="","",H17+COUNTIF($H$9:H17,H17)-1) | K17: =IFERROR(INDEX($H$9:$H$23,MATCH(9,$I$9:$I$23,0)),"") | L17: =IFERROR(INDEX($B$9:$B$23,MATCH(9,$I$9:$I$23,0)),"") | M17: =IFERROR(INDEX($G$9:$G$23,MATCH(9,$I$9:$I$23,0)),"")
A18: 10 | G18: =IF(COUNT(C18:F18)<4,"",SUMPRODUCT($C$5:$F$5,C18:F18)) | H18: =IF(G18="","",COUNTIF($G$9:$G$23,">"&(G18+0.005))+1) | I18: =IF(H18="","",H18+COUNTIF($H$9:H18,H18)-1) | K18: =IFERROR(INDEX($H$9:$H$23,MATCH(10,$I$9:$I$23,0)),"") | L18: =IFERROR(INDEX($B$9:$B$23,MATCH(10,$I$9:$I$23,0)),"") | M18: =IFERROR(INDEX($G$9:$G$23,MATCH(10,$I$9:$I$23,0)),"")
A19: 11 | G19: =IF(COUNT(C19:F19)<4,"",SUMPRODUCT($C$5:$F$5,C19:F19)) | H19: =IF(G19="","",COUNTIF($G$9:$G$23,">"&(G19+0.005))+1) | I19: =IF(H19="","",H19+COUNTIF($H$9:H19,H19)-1) | K19: =IFERROR(INDEX($H$9:$H$23,MATCH(11,$I$9:$I$23,0)),"") | L19: =IFERROR(INDEX($B$9:$B$23,MATCH(11,$I$9:$I$23,0)),"") | M19: =IFERROR(INDEX($G$9:$G$23,MATCH(11,$I$9:$I$23,0)),"")
A20: 12 | G20: =IF(COUNT(C20:F20)<4,"",SUMPRODUCT($C$5:$F$5,C20:F20)) | H20: =IF(G20="","",COUNTIF($G$9:$G$23,">"&(G20+0.005))+1) | I20: =IF(H20="","",H20+COUNTIF($H$9:H20,H20)-1) | K20: =IFERROR(INDEX($H$9:$H$23,MATCH(12,$I$9:$I$23,0)),"") | L20: =IFERROR(INDEX($B$9:$B$23,MATCH(12,$I$9:$I$23,0)),"") | M20: =IFERROR(INDEX($G$9:$G$23,MATCH(12,$I$9:$I$23,0)),"")
A21: 13 | G21: =IF(COUNT(C21:F21)<4,"",SUMPRODUCT($C$5:$F$5,C21:F21)) | H21: =IF(G21="","",COUNTIF($G$9:$G$23,">"&(G21+0.005))+1) | I21: =IF(H21="","",H21+COUNTIF($H$9:H21,H21)-1) | K21: =IFERROR(INDEX($H$9:$H$23,MATCH(13,$I$9:$I$23,0)),"") | L21: =IFERROR(INDEX($B$9:$B$23,MATCH(13,$I$9:$I$23,0)),"") | M21: =IFERROR(INDEX($G$9:$G$23,MATCH(13,$I$9:$I$23,0)),"")
A22: 14 | G22: =IF(COUNT(C22:F22)<4,"",SUMPRODUCT($C$5:$F$5,C22:F22)) | H22: =IF(G22="","",COUNTIF($G$9:$G$23,">"&(G22+0.005))+1) | I22: =IF(H22="","",H22+COUNTIF($H$9:H22,H22)-1) | K22: =IFERROR(INDEX($H$9:$H$23,MATCH(14,$I$9:$I$23,0)),"") | L22: =IFERROR(INDEX($B$9:$B$23,MATCH(14,$I$9:$I$23,0)),"") | M22: =IFERROR(INDEX($G$9:$G$23,MATCH(14,$I$9:$I$23,0)),"")
A23: 15 | G23: =IF(COUNT(C23:F23)<4,"",SUMPRODUCT($C$5:$F$5,C23:F23)) | H23: =IF(G23="","",COUNTIF($G$9:$G$23,">"&(G23+0.005))+1) | I23: =IF(H23="","",H23+COUNTIF($H$9:H23,H23)-1) | K23: =IFERROR(INDEX($H$9:$H$23,MATCH(15,$I$9:$I$23,0)),"") | L23: =IFERROR(INDEX($B$9:$B$23,MATCH(15,$I$9:$I$23,0)),"") | M23: =IFERROR(INDEX($G$9:$G$23,MATCH(15,$I$9:$I$23,0)),"")
B25: Criteria anchors: agree these with the weights, BEFORE anyone scores
B26: Criterion | C26: 1 means | F26: 5 means
B27: Lift
B28: Revenue
B29: Strategic
B30: Ease
B32: Weighted total = SUMPRODUCT(weights, scores). Equal totals share a rank.
B33: Weights and anchors are agreed, written down and dated before scoring. Change them after scoring and the ranking is chosen first, justified second.
B34: Like RICE, this tab has no column for time: deadlines are priced by Cost of Delay.

Sheet ICE · experiments
A1: ICE · small experiments
A2: For a pile of small, cheap tests, not roadmap bets. Impact, Confidence, Ease: 1-10 each, multiplied.
A4: # | B4: Experiment idea | C4: Impact | D4: Confidence | E4: Ease | F4: ICE score | G4: Rank
A5: 1 | B5: "Pay now" button in the reminder email | C5: 7 | D5: 8 | E5: 9 | F5: =IF(COUNT(C5:E5)<3,"",C5*D5*E5) | G5: =IF(F5="","",RANK(F5,$F$5:$F$19))
A6: 2 | B6: Reminder three days before the due date | C6: 6 | D6: 5 | E6: 8 | F6: =IF(COUNT(C6:E6)<3,"",C6*D6*E6) | G6: =IF(F6="","",RANK(F6,$F$5:$F$19))
A7: 3 | B7: Friendlier subject line | C7: 3 | D7: 6 | E7: 10 | F7: =IF(COUNT(C7:E7)<3,"",C7*D7*E7) | G7: =IF(F7="","",RANK(F7,$F$5:$F$19))
A8: 4 | B8: SMS reminders | C8: 6 | D8: 4 | E8: 3 | F8: =IF(COUNT(C8:E8)<3,"",C8*D8*E8) | G8: =IF(F8="","",RANK(F8,$F$5:$F$19))
A9: 5 | B9: Show the business its client's payment history | C9: 4 | D9: 3 | E9: 5 | F9: =IF(COUNT(C9:E9)<3,"",C9*D9*E9) | G9: =IF(F9="","",RANK(F9,$F$5:$F$19))
A10: 6 | F10: =IF(COUNT(C10:E10)<3,"",C10*D10*E10) | G10: =IF(F10="","",RANK(F10,$F$5:$F$19))
A11: 7 | F11: =IF(COUNT(C11:E11)<3,"",C11*D11*E11) | G11: =IF(F11="","",RANK(F11,$F$5:$F$19))
A12: 8 | F12: =IF(COUNT(C12:E12)<3,"",C12*D12*E12) | G12: =IF(F12="","",RANK(F12,$F$5:$F$19))
A13: 9 | F13: =IF(COUNT(C13:E13)<3,"",C13*D13*E13) | G13: =IF(F13="","",RANK(F13,$F$5:$F$19))
A14: 10 | F14: =IF(COUNT(C14:E14)<3,"",C14*D14*E14) | G14: =IF(F14="","",RANK(F14,$F$5:$F$19))
A15: 11 | F15: =IF(COUNT(C15:E15)<3,"",C15*D15*E15) | G15: =IF(F15="","",RANK(F15,$F$5:$F$19))
A16: 12 | F16: =IF(COUNT(C16:E16)<3,"",C16*D16*E16) | G16: =IF(F16="","",RANK(F16,$F$5:$F$19))
A17: 13 | F17: =IF(COUNT(C17:E17)<3,"",C17*D17*E17) | G17: =IF(F17="","",RANK(F17,$F$5:$F$19))
A18: 14 | F18: =IF(COUNT(C18:E18)<3,"",C18*D18*E18) | G18: =IF(F18="","",RANK(F18,$F$5:$F$19))
A19: 15 | F19: =IF(COUNT(C19:E19)<3,"",C19*D19*E19) | G19: =IF(F19="","",RANK(F19,$F$5:$F$19))
B21: Rows 1-5: the Get Paid squad's reminder-email ideas (Tallyrow, invented). Rows 6-15: yours.
B22: ICE is credited to Sean Ellis. Three unanchored 1-10 guesses are easy to inflate: keep it for cheap tests.

Sheet MoSCoW · Tallyrow
A1: MoSCoW · Tallyrow quarter
A2: The agreed board: every Must passed one of the four tests. Change a category and watch the bar.
B4: Capacity this timebox (person-months) | D4: 10
A6: # | B6: Item | C6: Requested by | D6: Effort (p-m) | E6: Category | F6: Why · which test? | H6: Category | I6: Person-months | J6: % of capacity | K6: Bar (█ = ½ person-month) | L6: Check
A7: 1 | B7: Payment link | C7: Priya (Support) | D7: 2 | E7: Must | F7: No point delivering the quarter without it (getting paid) | H7: Capacity | I7: =IF($D$4="","",$D$4) | J7: =IF(OR($D$4="",I7=""),"",I7/$D$4) | K7: =IF(OR($D$4="",I7=""),"",REPT("░",ROUND(I7*2,0)))
A8: 2 | B8: Smart reminders | C8: Maya (CEO) | D8: 4 | E8: Won't | F8: Fails every test; untested. Full build: not this time | H8: Must limit (~60%) | I8: =IF($D$4="","",$D$4*0.6) | J8: =IF(OR($D$4="",I8=""),"",I8/$D$4) | K8: =IF(OR($D$4="",I8=""),"",REPT("░",ROUND(I8*2,0)))
A9: 3 | B9: Recurring invoices | C9: Customers (top request) | D9: 2 | E9: Should | F9: Most requested; painful to leave out, nothing breaks | H9: Must | I9: =SUMIF($E$7:$E$20,"Must",$D$7:$D$20) | J9: =IF(OR($D$4="",I9=""),"",I9/$D$4) | K9: =IF(OR($D$4="",I9=""),"",REPT("█",ROUND(I9*2,0))) | L9: =IF(OR($D$4="",I9=0),"",IF(ROUND(J9,4)<=0.6,"✓ within 60%","✗ over 60%"))
A10: 4 | B10: E-invoicing | C10: Aisha (Compliance) | D10: 4 | E10: Must | F10: Not legal without it (one market) | H10: Should | I10: =SUMIF($E$7:$E$20,"Should",$D$7:$D$20) | J10: =IF(OR($D$4="",I10=""),"",I10/$D$4) | K10: =IF(OR($D$4="",I10=""),"",REPT("█",ROUND(I10*2,0)))
A11: 5 | B11: Multi-currency | C11: Daniel (Sales) | D11: 2 | E11: Won't | F11: Release works without it. Tell Daniel now | H11: Could | I11: =SUMIF($E$7:$E$20,"Could",$D$7:$D$20) | J11: =IF(OR($D$4="",I11=""),"",I11/$D$4) | K11: =IF(OR($D$4="",I11=""),"",REPT("█",ROUND(I11*2,0))) | L11: =IF(I11>0,"contingency: drop first","")
A12: 6 | B12: Client portal | C12: Design team | D12: 6 | E12: Won't | F12: Not this time | H12: Planned total | I12: =I9+I10+I11 | J12: =IF(OR($D$4="",I12=""),"",I12/$D$4) | K12: =IF(OR($D$4="",I12=""),"",REPT("█",ROUND(I12*2,0))) | L12: =IF(OR($D$4="",I12=0),"",IF(ROUND(J12,4)<=1,"✓ fits capacity","✗ over capacity"))
A13: 7 | B13: Late-fee automation | C13: Tomás (Finance) | D13: 2 | E13: Won't | F13: Not this time | H13: Won't (this time) | I13: =COUNTIF($E$7:$E$20,"Won't") | L13: =IF(I13=1,"item",IF(I13>1,"items",""))
A14: 8 | B14: Receipt capture | C14: User survey | D14: 4 | E14: Won't | F14: Not this time
A15: 9 | B15: Reminders concierge test | C15: Maya (CEO) | D15: 0.5 | E15: Could | F15: Support times reminders by hand for volunteer businesses
A16: 10 | B16: Reminders minimal version | C16: Maya (CEO) | D16: 1.5 | E16: Could | F16: Only if the concierge test passes. Dropped first
A17: 11
A18: 12
A19: 13
A20: 14
B22: The four Must tests (DSDM): a Must passes at least one
B23: 1. No point delivering on the date without it | F23: Payment link: the quarter is about getting paid
B24: 2. Not legal without it | F24: E-invoicing: one market's legal requirement
B25: 3. Unsafe without it
B26: 4. Cannot deliver a viable solution without it
B28: Must: the Minimum Usable SubseT the timebox guarantees to deliver.
B29: Should: important but not vital. Painful to leave out, may need a workaround; the release still works.
B30: Could: wanted but less important. Your contingency: the first thing dropped when a Must runs over.
B31: Won't (this time): agreed not to be delivered in this timebox. Not rejected, not forgotten.
B32: Musts typically no more than about 60% of the effort in the timebox; Coulds around 20%.
B33: MoSCoW scopes a fixed timebox; it does not rank. Inside the Musts, use another model to order the work.
B35: Source: MoSCoW, Dai Clegg (1994); DSDM, Agile Business Consortium, "MoSCoW Prioritisation".
B36: Every Tallyrow number is invented for teaching.

Sheet MoSCoW · your release
A1: MoSCoW · your next release
A2: Step 1: enter your capacity in person-months. Step 2: list every item with its effort. Step 3: place each one, then add up the Musts.
B4: Capacity this timebox (person-months)
A6: # | B6: Item | C6: Requested by | D6: Effort (p-m) | E6: Category | F6: Why · which test? | H6: Category | I6: Person-months | J6: % of capacity | K6: Bar (█ = ½ person-month) | L6: Check
A7: 1 | H7: Capacity | I7: =IF($D$4="","",$D$4) | J7: =IF(OR($D$4="",I7=""),"",I7/$D$4) | K7: =IF(OR($D$4="",I7=""),"",REPT("░",ROUND(I7*2,0)))
A8: 2 | H8: Must limit (~60%) | I8: =IF($D$4="","",$D$4*0.6) | J8: =IF(OR($D$4="",I8=""),"",I8/$D$4) | K8: =IF(OR($D$4="",I8=""),"",REPT("░",ROUND(I8*2,0)))
A9: 3 | H9: Must | I9: =SUMIF($E$7:$E$26,"Must",$D$7:$D$26) | J9: =IF(OR($D$4="",I9=""),"",I9/$D$4) | K9: =IF(OR($D$4="",I9=""),"",REPT("█",ROUND(I9*2,0))) | L9: =IF(OR($D$4="",I9=0),"",IF(ROUND(J9,4)<=0.6,"✓ within 60%","✗ over 60%"))
A10: 4 | H10: Should | I10: =SUMIF($E$7:$E$26,"Should",$D$7:$D$26) | J10: =IF(OR($D$4="",I10=""),"",I10/$D$4) | K10: =IF(OR($D$4="",I10=""),"",REPT("█",ROUND(I10*2,0)))
A11: 5 | H11: Could | I11: =SUMIF($E$7:$E$26,"Could",$D$7:$D$26) | J11: =IF(OR($D$4="",I11=""),"",I11/$D$4) | K11: =IF(OR($D$4="",I11=""),"",REPT("█",ROUND(I11*2,0))) | L11: =IF(I11>0,"contingency: drop first","")
A12: 6 | H12: Planned total | I12: =I9+I10+I11 | J12: =IF(OR($D$4="",I12=""),"",I12/$D$4) | K12: =IF(OR($D$4="",I12=""),"",REPT("█",ROUND(I12*2,0))) | L12: =IF(OR($D$4="",I12=0),"",IF(ROUND(J12,4)<=1,"✓ fits capacity","✗ over capacity"))
A13: 7 | H13: Won't (this time) | I13: =COUNTIF($E$7:$E$26,"Won't") | L13: =IF(I13=1,"item",IF(I13>1,"items",""))
A14: 8
A15: 9
A16: 10
A17: 11
A18: 12
A19: 13
A20: 14
A21: 15
A22: 16
A23: 17
A24: 18
A25: 19
A26: 20
B28: The four Must tests (DSDM): a Must passes at least one
B29: 1. No point delivering on the date without it
B30: 2. Not legal without it
B31: 3. Unsafe without it
B32: 4. Cannot deliver a viable solution without it
B34: Must: the Minimum Usable SubseT the timebox guarantees to deliver.
B35: Should: important but not vital. Painful to leave out, may need a workaround; the release still works.
B36: Could: wanted but less important. Your contingency: the first thing dropped when a Must runs over.
B37: Won't (this time): agreed not to be delivered in this timebox. Not rejected, not forgotten.
B38: Musts typically no more than about 60% of the effort in the timebox; Coulds around 20%.
B39: MoSCoW scopes a fixed timebox; it does not rank. Inside the Musts, use another model to order the work.
B41: Source: MoSCoW, Dai Clegg (1994); DSDM, Agile Business Consortium, "MoSCoW Prioritisation".

Sheet CD3 · Tallyrow
A1: CD3 · Tallyrow backlog
A2: Weekly cost of delay ÷ weeks of work. Then check the dates block: CD3 cannot see a deadline.
B4: CD3 = cost of delay ÷ duration. Start with the highest.
A6: # | B6: Item | C6: Urgency profile | D6: Cost of delay ($k / week) | E6: Duration (weeks) | F6: CD3 | G6: Rank | J6: Rank | K6: Ranked view | L6: CD3
A7: 1 | B7: Payment link | C7: Long, peak unaffected | D7: 15 | E7: 4 | F7: =IF(COUNT(D7:E7)<2,"",ROUND(D7/E7,3)) | G7: =IF(COUNT(F7)=0,"",COUNTIF($F$7:$F$14,">"&(F7+0.0005))+1) | H7: =IF(G7="","",G7+COUNTIF($G$7:G7,G7)-1) | J7: =IFERROR(INDEX($G$7:$G$14,MATCH(1,$H$7:$H$14,0)),"") | K7: =IFERROR(INDEX($B$7:$B$14,MATCH(1,$H$7:$H$14,0)),"") | L7: =IFERROR(INDEX($F$7:$F$14,MATCH(1,$H$7:$H$14,0)),"")
A8: 2 | B8: Smart reminders | C8: Long, peak affected | D8: 10 | E8: 8 | F8: =IF(COUNT(D8:E8)<2,"",ROUND(D8/E8,3)) | G8: =IF(COUNT(F8)=0,"",COUNTIF($F$7:$F$14,">"&(F8+0.0005))+1) | H8: =IF(G8="","",G8+COUNTIF($G$7:G8,G8)-1) | J8: =IFERROR(INDEX($G$7:$G$14,MATCH(2,$H$7:$H$14,0)),"") | K8: =IFERROR(INDEX($B$7:$B$14,MATCH(2,$H$7:$H$14,0)),"") | L8: =IFERROR(INDEX($F$7:$F$14,MATCH(2,$H$7:$H$14,0)),"")
A9: 3 | B9: Recurring invoices | C9: Long, peak unaffected | D9: 6 | E9: 4 | F9: =IF(COUNT(D9:E9)<2,"",ROUND(D9/E9,3)) | G9: =IF(COUNT(F9)=0,"",COUNTIF($F$7:$F$14,">"&(F9+0.0005))+1) | H9: =IF(G9="","",G9+COUNTIF($G$7:G9,G9)-1) | J9: =IFERROR(INDEX($G$7:$G$14,MATCH(3,$H$7:$H$14,0)),"") | K9: =IFERROR(INDEX($B$7:$B$14,MATCH(3,$H$7:$H$14,0)),"") | L9: =IFERROR(INDEX($F$7:$F$14,MATCH(3,$H$7:$H$14,0)),"")
A10: 4 | B10: E-invoicing | C10: External deadline | D10: 0 | E10: 8 | F10: =IF(COUNT(D10:E10)<2,"",ROUND(D10/E10,3)) | G10: =IF(COUNT(F10)=0,"",COUNTIF($F$7:$F$14,">"&(F10+0.0005))+1) | H10: =IF(G10="","",G10+COUNTIF($G$7:G10,G10)-1) | J10: =IFERROR(INDEX($G$7:$G$14,MATCH(4,$H$7:$H$14,0)),"") | K10: =IFERROR(INDEX($B$7:$B$14,MATCH(4,$H$7:$H$14,0)),"") | L10: =IFERROR(INDEX($F$7:$F$14,MATCH(4,$H$7:$H$14,0)),"")
A11: 5 | B11: Multi-currency | C11: Treated as steady | D11: 1.2 | E11: 4 | F11: =IF(COUNT(D11:E11)<2,"",ROUND(D11/E11,3)) | G11: =IF(COUNT(F11)=0,"",COUNTIF($F$7:$F$14,">"&(F11+0.0005))+1) | H11: =IF(G11="","",G11+COUNTIF($G$7:G11,G11)-1) | J11: =IFERROR(INDEX($G$7:$G$14,MATCH(5,$H$7:$H$14,0)),"") | K11: =IFERROR(INDEX($B$7:$B$14,MATCH(5,$H$7:$H$14,0)),"") | L11: =IFERROR(INDEX($F$7:$F$14,MATCH(5,$H$7:$H$14,0)),"")
A12: 6 | B12: Client portal | C12: Long, peak unaffected | D12: 3 | E12: 12 | F12: =IF(COUNT(D12:E12)<2,"",ROUND(D12/E12,3)) | G12: =IF(COUNT(F12)=0,"",COUNTIF($F$7:$F$14,">"&(F12+0.0005))+1) | H12: =IF(G12="","",G12+COUNTIF($G$7:G12,G12)-1) | J12: =IFERROR(INDEX($G$7:$G$14,MATCH(6,$H$7:$H$14,0)),"") | K12: =IFERROR(INDEX($B$7:$B$14,MATCH(6,$H$7:$H$14,0)),"") | L12: =IFERROR(INDEX($F$7:$F$14,MATCH(6,$H$7:$H$14,0)),"")
A13: 7 | B13: Late-fee automation | C13: Long, peak unaffected | D13: 4 | E13: 4 | F13: =IF(COUNT(D13:E13)<2,"",ROUND(D13/E13,3)) | G13: =IF(COUNT(F13)=0,"",COUNTIF($F$7:$F$14,">"&(F13+0.0005))+1) | H13: =IF(G13="","",G13+COUNTIF($G$7:G13,G13)-1) | J13: =IFERROR(INDEX($G$7:$G$14,MATCH(7,$H$7:$H$14,0)),"") | K13: =IFERROR(INDEX($B$7:$B$14,MATCH(7,$H$7:$H$14,0)),"") | L13: =IFERROR(INDEX($F$7:$F$14,MATCH(7,$H$7:$H$14,0)),"")
A14: 8 | B14: Receipt capture | C14: Long, peak unaffected | D14: 1 | E14: 8 | F14: =IF(COUNT(D14:E14)<2,"",ROUND(D14/E14,3)) | G14: =IF(COUNT(F14)=0,"",COUNTIF($F$7:$F$14,">"&(F14+0.0005))+1) | H14: =IF(G14="","",G14+COUNTIF($G$7:G14,G14)-1) | J14: =IFERROR(INDEX($G$7:$G$14,MATCH(8,$H$7:$H$14,0)),"") | K14: =IFERROR(INDEX($B$7:$B$14,MATCH(8,$H$7:$H$14,0)),"") | L14: =IFERROR(INDEX($F$7:$F$14,MATCH(8,$H$7:$H$14,0)),"")
B16: Dates first: schedule date-bound work backwards from its date, BEFORE you sort by CD3
B17: Date-bound item | C17: Date (week of quarter) | D17: Delivery (weeks) | E17: Latest start (week) | F17: Buffer (weeks) | G17: Start by
B18: E-invoicing | C18: 12 | D18: 8 | E18: =IF(COUNT(C18:D18)<2,"",C18-D18) | F18: 1 | G18: =IF(E18="","","week "&(E18-N(F18)))
B20: Then let CD3 order everything else around it. Today's cost of delay for a deadline item is zero, so CD3 alone puts it last.
B22: Ranges: CD3 is only as good as the cost of delay you feed it
B23: Item | C23: CoD low ($k / week) | D23: CoD high ($k / week) | E23: Duration (weeks) | F23: CD3 low | G23: CD3 high
B24: Smart reminders | C24: 0 | D24: 20 | E24: 8 | F24: =IF(COUNT(C24,E24)<2,"",ROUND(C24/E24,3)) | G24: =IF(COUNT(D24,E24)<2,"",ROUND(D24/E24,3))
B26: CD3: Cost of Delay Divided by Duration (Black Swan Farming). Short, urgent items go first.
B27: Cost of delay in the same unit for every row ($ thousands per week here); duration in weeks.
B28: Profiles and weekly figures are the cost-of-delay estimates from the urgency-profiles lesson.
B29: Every Tallyrow number is invented for teaching.

Sheet CD3 · your top five
A1: CD3 · your top five
A2: Step 1: a weekly cost of delay and a duration per item. Step 2: any item with a date goes in the dates block first.
B4: CD3 = cost of delay ÷ duration. Start with the highest.
A6: # | B6: Item | C6: Urgency profile | D6: Cost of delay ($k / week) | E6: Duration (weeks) | F6: CD3 | G6: Rank | J6: Rank | K6: Ranked view | L6: CD3
A7: 1 | F7: =IF(COUNT(D7:E7)<2,"",ROUND(D7/E7,3)) | G7: =IF(COUNT(F7)=0,"",COUNTIF($F$7:$F$16,">"&(F7+0.0005))+1) | H7: =IF(G7="","",G7+COUNTIF($G$7:G7,G7)-1) | J7: =IFERROR(INDEX($G$7:$G$16,MATCH(1,$H$7:$H$16,0)),"") | K7: =IFERROR(INDEX($B$7:$B$16,MATCH(1,$H$7:$H$16,0)),"") | L7: =IFERROR(INDEX($F$7:$F$16,MATCH(1,$H$7:$H$16,0)),"")
A8: 2 | F8: =IF(COUNT(D8:E8)<2,"",ROUND(D8/E8,3)) | G8: =IF(COUNT(F8)=0,"",COUNTIF($F$7:$F$16,">"&(F8+0.0005))+1) | H8: =IF(G8="","",G8+COUNTIF($G$7:G8,G8)-1) | J8: =IFERROR(INDEX($G$7:$G$16,MATCH(2,$H$7:$H$16,0)),"") | K8: =IFERROR(INDEX($B$7:$B$16,MATCH(2,$H$7:$H$16,0)),"") | L8: =IFERROR(INDEX($F$7:$F$16,MATCH(2,$H$7:$H$16,0)),"")
A9: 3 | F9: =IF(COUNT(D9:E9)<2,"",ROUND(D9/E9,3)) | G9: =IF(COUNT(F9)=0,"",COUNTIF($F$7:$F$16,">"&(F9+0.0005))+1) | H9: =IF(G9="","",G9+COUNTIF($G$7:G9,G9)-1) | J9: =IFERROR(INDEX($G$7:$G$16,MATCH(3,$H$7:$H$16,0)),"") | K9: =IFERROR(INDEX($B$7:$B$16,MATCH(3,$H$7:$H$16,0)),"") | L9: =IFERROR(INDEX($F$7:$F$16,MATCH(3,$H$7:$H$16,0)),"")
A10: 4 | F10: =IF(COUNT(D10:E10)<2,"",ROUND(D10/E10,3)) | G10: =IF(COUNT(F10)=0,"",COUNTIF($F$7:$F$16,">"&(F10+0.0005))+1) | H10: =IF(G10="","",G10+COUNTIF($G$7:G10,G10)-1) | J10: =IFERROR(INDEX($G$7:$G$16,MATCH(4,$H$7:$H$16,0)),"") | K10: =IFERROR(INDEX($B$7:$B$16,MATCH(4,$H$7:$H$16,0)),"") | L10: =IFERROR(INDEX($F$7:$F$16,MATCH(4,$H$7:$H$16,0)),"")
A11: 5 | F11: =IF(COUNT(D11:E11)<2,"",ROUND(D11/E11,3)) | G11: =IF(COUNT(F11)=0,"",COUNTIF($F$7:$F$16,">"&(F11+0.0005))+1) | H11: =IF(G11="","",G11+COUNTIF($G$7:G11,G11)-1) | J11: =IFERROR(INDEX($G$7:$G$16,MATCH(5,$H$7:$H$16,0)),"") | K11: =IFERROR(INDEX($B$7:$B$16,MATCH(5,$H$7:$H$16,0)),"") | L11: =IFERROR(INDEX($F$7:$F$16,MATCH(5,$H$7:$H$16,0)),"")
A12: 6 | F12: =IF(COUNT(D12:E12)<2,"",ROUND(D12/E12,3)) | G12: =IF(COUNT(F12)=0,"",COUNTIF($F$7:$F$16,">"&(F12+0.0005))+1) | H12: =IF(G12="","",G12+COUNTIF($G$7:G12,G12)-1) | J12: =IFERROR(INDEX($G$7:$G$16,MATCH(6,$H$7:$H$16,0)),"") | K12: =IFERROR(INDEX($B$7:$B$16,MATCH(6,$H$7:$H$16,0)),"") | L12: =IFERROR(INDEX($F$7:$F$16,MATCH(6,$H$7:$H$16,0)),"")
A13: 7 | F13: =IF(COUNT(D13:E13)<2,"",ROUND(D13/E13,3)) | G13: =IF(COUNT(F13)=0,"",COUNTIF($F$7:$F$16,">"&(F13+0.0005))+1) | H13: =IF(G13="","",G13+COUNTIF($G$7:G13,G13)-1) | J13: =IFERROR(INDEX($G$7:$G$16,MATCH(7,$H$7:$H$16,0)),"") | K13: =IFERROR(INDEX($B$7:$B$16,MATCH(7,$H$7:$H$16,0)),"") | L13: =IFERROR(INDEX($F$7:$F$16,MATCH(7,$H$7:$H$16,0)),"")
A14: 8 | F14: =IF(COUNT(D14:E14)<2,"",ROUND(D14/E14,3)) | G14: =IF(COUNT(F14)=0,"",COUNTIF($F$7:$F$16,">"&(F14+0.0005))+1) | H14: =IF(G14="","",G14+COUNTIF($G$7:G14,G14)-1) | J14: =IFERROR(INDEX($G$7:$G$16,MATCH(8,$H$7:$H$16,0)),"") | K14: =IFERROR(INDEX($B$7:$B$16,MATCH(8,$H$7:$H$16,0)),"") | L14: =IFERROR(INDEX($F$7:$F$16,MATCH(8,$H$7:$H$16,0)),"")
A15: 9 | F15: =IF(COUNT(D15:E15)<2,"",ROUND(D15/E15,3)) | G15: =IF(COUNT(F15)=0,"",COUNTIF($F$7:$F$16,">"&(F15+0.0005))+1) | H15: =IF(G15="","",G15+COUNTIF($G$7:G15,G15)-1) | J15: =IFERROR(INDEX($G$7:$G$16,MATCH(9,$H$7:$H$16,0)),"") | K15: =IFERROR(INDEX($B$7:$B$16,MATCH(9,$H$7:$H$16,0)),"") | L15: =IFERROR(INDEX($F$7:$F$16,MATCH(9,$H$7:$H$16,0)),"")
A16: 10 | F16: =IF(COUNT(D16:E16)<2,"",ROUND(D16/E16,3)) | G16: =IF(COUNT(F16)=0,"",COUNTIF($F$7:$F$16,">"&(F16+0.0005))+1) | H16: =IF(G16="","",G16+COUNTIF($G$7:G16,G16)-1) | J16: =IFERROR(INDEX($G$7:$G$16,MATCH(10,$H$7:$H$16,0)),"") | K16: =IFERROR(INDEX($B$7:$B$16,MATCH(10,$H$7:$H$16,0)),"") | L16: =IFERROR(INDEX($F$7:$F$16,MATCH(10,$H$7:$H$16,0)),"")
B18: Dates first: schedule date-bound work backwards from its date, BEFORE you sort by CD3
B19: Date-bound item | C19: Date (week of quarter) | D19: Delivery (weeks) | E19: Latest start (week) | F19: Buffer (weeks) | G19: Start by
E20: =IF(COUNT(C20:D20)<2,"",C20-D20) | G20: =IF(E20="","","week "&(E20-N(F20)))
E21: =IF(COUNT(C21:D21)<2,"",C21-D21) | G21: =IF(E21="","","week "&(E21-N(F21)))
E22: =IF(COUNT(C22:D22)<2,"",C22-D22) | G22: =IF(E22="","","week "&(E22-N(F22)))
B24: Then let CD3 order everything else around it. Today's cost of delay for a deadline item is zero, so CD3 alone puts it last.
B26: Ranges: CD3 is only as good as the cost of delay you feed it
B27: Item | C27: CoD low ($k / week) | D27: CoD high ($k / week) | E27: Duration (weeks) | F27: CD3 low | G27: CD3 high
F28: =IF(COUNT(C28,E28)<2,"",ROUND(C28/E28,3)) | G28: =IF(COUNT(D28,E28)<2,"",ROUND(D28/E28,3))
F29: =IF(COUNT(C29,E29)<2,"",ROUND(C29/E29,3)) | G29: =IF(COUNT(D29,E29)<2,"",ROUND(D29/E29,3))
F30: =IF(COUNT(C30,E30)<2,"",ROUND(C30/E30,3)) | G30: =IF(COUNT(D30,E30)<2,"",ROUND(D30/E30,3))
B32: CD3: Cost of Delay Divided by Duration (Black Swan Farming). Short, urgent items go first.
B33: Cost of delay in the same unit for every row ($ thousands per week here); duration in weeks.

Sheet WSJF · Tallyrow
A1: WSJF · Tallyrow backlog
A2: SAFe's Weighted Shortest Job First on the same eight items. Watch the time criticality column.
B4: WSJF = (value + time criticality + risk / opportunity) ÷ job size
A6: # | B6: Item | C6: User-business value | D6: Time criticality | E6: Risk reduction / opportunity enablement | F6: Cost of delay (sum) | G6: Job size | H6: WSJF | I6: Rank | L6: Rank | M6: Ranked view | N6: WSJF
A7: 1 | B7: Payment link | C7: 13 | D7: 8 | E7: 3 | F7: =IF(COUNT(C7:E7)<3,"",SUM(C7:E7)) | G7: 1 | H7: =IF(OR(F7="",N(G7)=0),"",ROUND(F7/G7,2)) | I7: =IF(H7="","",COUNTIF($H$7:$H$14,">"&(H7+0.005))+1) | J7: =IF(I7="","",I7+COUNTIF($I$7:I7,I7)-1) | L7: =IFERROR(INDEX($I$7:$I$14,MATCH(1,$J$7:$J$14,0)),"") | M7: =IFERROR(INDEX($B$7:$B$14,MATCH(1,$J$7:$J$14,0)),"") | N7: =IFERROR(INDEX($H$7:$H$14,MATCH(1,$J$7:$J$14,0)),"")
A8: 2 | B8: Smart reminders | C8: 8 | D8: 5 | E8: 8 | F8: =IF(COUNT(C8:E8)<3,"",SUM(C8:E8)) | G8: 2 | H8: =IF(OR(F8="",N(G8)=0),"",ROUND(F8/G8,2)) | I8: =IF(H8="","",COUNTIF($H$7:$H$14,">"&(H8+0.005))+1) | J8: =IF(I8="","",I8+COUNTIF($I$7:I8,I8)-1) | L8: =IFERROR(INDEX($I$7:$I$14,MATCH(2,$J$7:$J$14,0)),"") | M8: =IFERROR(INDEX($B$7:$B$14,MATCH(2,$J$7:$J$14,0)),"") | N8: =IFERROR(INDEX($H$7:$H$14,MATCH(2,$J$7:$J$14,0)),"")
A9: 3 | B9: Recurring invoices | C9: 8 | D9: 3 | E9: 2 | F9: =IF(COUNT(C9:E9)<3,"",SUM(C9:E9)) | G9: 1 | H9: =IF(OR(F9="",N(G9)=0),"",ROUND(F9/G9,2)) | I9: =IF(H9="","",COUNTIF($H$7:$H$14,">"&(H9+0.005))+1) | J9: =IF(I9="","",I9+COUNTIF($I$7:I9,I9)-1) | L9: =IFERROR(INDEX($I$7:$I$14,MATCH(3,$J$7:$J$14,0)),"") | M9: =IFERROR(INDEX($B$7:$B$14,MATCH(3,$J$7:$J$14,0)),"") | N9: =IFERROR(INDEX($H$7:$H$14,MATCH(3,$J$7:$J$14,0)),"")
A10: 4 | B10: E-invoicing | C10: 5 | D10: 20 | E10: 8 | F10: =IF(COUNT(C10:E10)<3,"",SUM(C10:E10)) | G10: 2 | H10: =IF(OR(F10="",N(G10)=0),"",ROUND(F10/G10,2)) | I10: =IF(H10="","",COUNTIF($H$7:$H$14,">"&(H10+0.005))+1) | J10: =IF(I10="","",I10+COUNTIF($I$7:I10,I10)-1) | L10: =IFERROR(INDEX($I$7:$I$14,MATCH(4,$J$7:$J$14,0)),"") | M10: =IFERROR(INDEX($B$7:$B$14,MATCH(4,$J$7:$J$14,0)),"") | N10: =IFERROR(INDEX($H$7:$H$14,MATCH(4,$J$7:$J$14,0)),"")
A11: 5 | B11: Multi-currency | C11: 3 | D11: 8 | E11: 1 | F11: =IF(COUNT(C11:E11)<3,"",SUM(C11:E11)) | G11: 1 | H11: =IF(OR(F11="",N(G11)=0),"",ROUND(F11/G11,2)) | I11: =IF(H11="","",COUNTIF($H$7:$H$14,">"&(H11+0.005))+1) | J11: =IF(I11="","",I11+COUNTIF($I$7:I11,I11)-1) | L11: =IFERROR(INDEX($I$7:$I$14,MATCH(5,$J$7:$J$14,0)),"") | M11: =IFERROR(INDEX($B$7:$B$14,MATCH(5,$J$7:$J$14,0)),"") | N11: =IFERROR(INDEX($H$7:$H$14,MATCH(5,$J$7:$J$14,0)),"")
A12: 6 | B12: Client portal | C12: 5 | D12: 1 | E12: 2 | F12: =IF(COUNT(C12:E12)<3,"",SUM(C12:E12)) | G12: 3 | H12: =IF(OR(F12="",N(G12)=0),"",ROUND(F12/G12,2)) | I12: =IF(H12="","",COUNTIF($H$7:$H$14,">"&(H12+0.005))+1) | J12: =IF(I12="","",I12+COUNTIF($I$7:I12,I12)-1) | L12: =IFERROR(INDEX($I$7:$I$14,MATCH(6,$J$7:$J$14,0)),"") | M12: =IFERROR(INDEX($B$7:$B$14,MATCH(6,$J$7:$J$14,0)),"") | N12: =IFERROR(INDEX($H$7:$H$14,MATCH(6,$J$7:$J$14,0)),"")
A13: 7 | B13: Late-fee automation | C13: 5 | D13: 2 | E13: 1 | F13: =IF(COUNT(C13:E13)<3,"",SUM(C13:E13)) | G13: 1 | H13: =IF(OR(F13="",N(G13)=0),"",ROUND(F13/G13,2)) | I13: =IF(H13="","",COUNTIF($H$7:$H$14,">"&(H13+0.005))+1) | J13: =IF(I13="","",I13+COUNTIF($I$7:I13,I13)-1) | L13: =IFERROR(INDEX($I$7:$I$14,MATCH(7,$J$7:$J$14,0)),"") | M13: =IFERROR(INDEX($B$7:$B$14,MATCH(7,$J$7:$J$14,0)),"") | N13: =IFERROR(INDEX($H$7:$H$14,MATCH(7,$J$7:$J$14,0)),"")
A14: 8 | B14: Receipt capture | C14: 1 | D14: 1 | E14: 1 | F14: =IF(COUNT(C14:E14)<3,"",SUM(C14:E14)) | G14: 2 | H14: =IF(OR(F14="",N(G14)=0),"",ROUND(F14/G14,2)) | I14: =IF(H14="","",COUNTIF($H$7:$H$14,">"&(H14+0.005))+1) | J14: =IF(I14="","",I14+COUNTIF($I$7:I14,I14)-1) | L14: =IFERROR(INDEX($I$7:$I$14,MATCH(8,$J$7:$J$14,0)),"") | M14: =IFERROR(INDEX($B$7:$B$14,MATCH(8,$J$7:$J$14,0)),"") | N14: =IFERROR(INDEX($H$7:$H$14,MATCH(8,$J$7:$J$14,0)),"")
B15: Smallest item = 1? | C15: =IF(COUNT(C7:C14)=0,"",IF(COUNTIF(C7:C14,1)=0,"✗ no 1",IF(COUNT(C7:C14)=COUNTIF(C7:C14,1)+COUNTIF(C7:C14,2)+COUNTIF(C7:C14,3)+COUNTIF(C7:C14,5)+COUNTIF(C7:C14,8)+COUNTIF(C7:C14,13)+COUNTIF(C7:C14,20),"✓","✗ scale"))) | D15: =IF(COUNT(D7:D14)=0,"",IF(COUNTIF(D7:D14,1)=0,"✗ no 1",IF(COUNT(D7:D14)=COUNTIF(D7:D14,1)+COUNTIF(D7:D14,2)+COUNTIF(D7:D14,3)+COUNTIF(D7:D14,5)+COUNTIF(D7:D14,8)+COUNTIF(D7:D14,13)+COUNTIF(D7:D14,20),"✓","✗ scale"))) | E15: =IF(COUNT(E7:E14)=0,"",IF(COUNTIF(E7:E14,1)=0,"✗ no 1",IF(COUNT(E7:E14)=COUNTIF(E7:E14,1)+COUNTIF(E7:E14,2)+COUNTIF(E7:E14,3)+COUNTIF(E7:E14,5)+COUNTIF(E7:E14,8)+COUNTIF(E7:E14,13)+COUNTIF(E7:E14,20),"✓","✗ scale"))) | G15: =IF(COUNT(G7:G14)=0,"",IF(COUNTIF(G7:G14,1)=0,"✗ no 1",IF(COUNT(G7:G14)=COUNTIF(G7:G14,1)+COUNTIF(G7:G14,2)+COUNTIF(G7:G14,3)+COUNTIF(G7:G14,5)+COUNTIF(G7:G14,8)+COUNTIF(G7:G14,13)+COUNTIF(G7:G14,20),"✓","✗ scale")))
B17: Modified Fibonacci scale: 1, 2, 3, 5, 8, 13, 20. Estimate ONE column at a time: the smallest item in the column gets a 1, everything else is sized against it.
B18: User-business value: how much users or the business gain. Time criticality: how fast the value decays, or whether a date is coming.
B19: Risk reduction / opportunity enablement: does doing it make other work safer, or possible?
B20: Job size stands in for duration. SAFe calls it a proxy: dependencies can override the order.
B21: Source: WSJF as defined by SAFe (Scaled Agile Framework).
B22: Every Tallyrow number is invented for teaching.

Sheet WSJF · your backlog
A1: WSJF · your backlog
A2: List the items, then fill one column at a time. In each column, the smallest item gets a 1.
B4: WSJF = (value + time criticality + risk / opportunity) ÷ job size
A6: # | B6: Item | C6: User-business value | D6: Time criticality | E6: Risk reduction / opportunity enablement | F6: Cost of delay (sum) | G6: Job size | H6: WSJF | I6: Rank | L6: Rank | M6: Ranked view | N6: WSJF
A7: 1 | F7: =IF(COUNT(C7:E7)<3,"",SUM(C7:E7)) | H7: =IF(OR(F7="",N(G7)=0),"",ROUND(F7/G7,2)) | I7: =IF(H7="","",COUNTIF($H$7:$H$21,">"&(H7+0.005))+1) | J7: =IF(I7="","",I7+COUNTIF($I$7:I7,I7)-1) | L7: =IFERROR(INDEX($I$7:$I$21,MATCH(1,$J$7:$J$21,0)),"") | M7: =IFERROR(INDEX($B$7:$B$21,MATCH(1,$J$7:$J$21,0)),"") | N7: =IFERROR(INDEX($H$7:$H$21,MATCH(1,$J$7:$J$21,0)),"")
A8: 2 | F8: =IF(COUNT(C8:E8)<3,"",SUM(C8:E8)) | H8: =IF(OR(F8="",N(G8)=0),"",ROUND(F8/G8,2)) | I8: =IF(H8="","",COUNTIF($H$7:$H$21,">"&(H8+0.005))+1) | J8: =IF(I8="","",I8+COUNTIF($I$7:I8,I8)-1) | L8: =IFERROR(INDEX($I$7:$I$21,MATCH(2,$J$7:$J$21,0)),"") | M8: =IFERROR(INDEX($B$7:$B$21,MATCH(2,$J$7:$J$21,0)),"") | N8: =IFERROR(INDEX($H$7:$H$21,MATCH(2,$J$7:$J$21,0)),"")
A9: 3 | F9: =IF(COUNT(C9:E9)<3,"",SUM(C9:E9)) | H9: =IF(OR(F9="",N(G9)=0),"",ROUND(F9/G9,2)) | I9: =IF(H9="","",COUNTIF($H$7:$H$21,">"&(H9+0.005))+1) | J9: =IF(I9="","",I9+COUNTIF($I$7:I9,I9)-1) | L9: =IFERROR(INDEX($I$7:$I$21,MATCH(3,$J$7:$J$21,0)),"") | M9: =IFERROR(INDEX($B$7:$B$21,MATCH(3,$J$7:$J$21,0)),"") | N9: =IFERROR(INDEX($H$7:$H$21,MATCH(3,$J$7:$J$21,0)),"")
A10: 4 | F10: =IF(COUNT(C10:E10)<3,"",SUM(C10:E10)) | H10: =IF(OR(F10="",N(G10)=0),"",ROUND(F10/G10,2)) | I10: =IF(H10="","",COUNTIF($H$7:$H$21,">"&(H10+0.005))+1) | J10: =IF(I10="","",I10+COUNTIF($I$7:I10,I10)-1) | L10: =IFERROR(INDEX($I$7:$I$21,MATCH(4,$J$7:$J$21,0)),"") | M10: =IFERROR(INDEX($B$7:$B$21,MATCH(4,$J$7:$J$21,0)),"") | N10: =IFERROR(INDEX($H$7:$H$21,MATCH(4,$J$7:$J$21,0)),"")
A11: 5 | F11: =IF(COUNT(C11:E11)<3,"",SUM(C11:E11)) | H11: =IF(OR(F11="",N(G11)=0),"",ROUND(F11/G11,2)) | I11: =IF(H11="","",COUNTIF($H$7:$H$21,">"&(H11+0.005))+1) | J11: =IF(I11="","",I11+COUNTIF($I$7:I11,I11)-1) | L11: =IFERROR(INDEX($I$7:$I$21,MATCH(5,$J$7:$J$21,0)),"") | M11: =IFERROR(INDEX($B$7:$B$21,MATCH(5,$J$7:$J$21,0)),"") | N11: =IFERROR(INDEX($H$7:$H$21,MATCH(5,$J$7:$J$21,0)),"")
A12: 6 | F12: =IF(COUNT(C12:E12)<3,"",SUM(C12:E12)) | H12: =IF(OR(F12="",N(G12)=0),"",ROUND(F12/G12,2)) | I12: =IF(H12="","",COUNTIF($H$7:$H$21,">"&(H12+0.005))+1) | J12: =IF(I12="","",I12+COUNTIF($I$7:I12,I12)-1) | L12: =IFERROR(INDEX($I$7:$I$21,MATCH(6,$J$7:$J$21,0)),"") | M12: =IFERROR(INDEX($B$7:$B$21,MATCH(6,$J$7:$J$21,0)),"") | N12: =IFERROR(INDEX($H$7:$H$21,MATCH(6,$J$7:$J$21,0)),"")
A13: 7 | F13: =IF(COUNT(C13:E13)<3,"",SUM(C13:E13)) | H13: =IF(OR(F13="",N(G13)=0),"",ROUND(F13/G13,2)) | I13: =IF(H13="","",COUNTIF($H$7:$H$21,">"&(H13+0.005))+1) | J13: =IF(I13="","",I13+COUNTIF($I$7:I13,I13)-1) | L13: =IFERROR(INDEX($I$7:$I$21,MATCH(7,$J$7:$J$21,0)),"") | M13: =IFERROR(INDEX($B$7:$B$21,MATCH(7,$J$7:$J$21,0)),"") | N13: =IFERROR(INDEX($H$7:$H$21,MATCH(7,$J$7:$J$21,0)),"")
A14: 8 | F14: =IF(COUNT(C14:E14)<3,"",SUM(C14:E14)) | H14: =IF(OR(F14="",N(G14)=0),"",ROUND(F14/G14,2)) | I14: =IF(H14="","",COUNTIF($H$7:$H$21,">"&(H14+0.005))+1) | J14: =IF(I14="","",I14+COUNTIF($I$7:I14,I14)-1) | L14: =IFERROR(INDEX($I$7:$I$21,MATCH(8,$J$7:$J$21,0)),"") | M14: =IFERROR(INDEX($B$7:$B$21,MATCH(8,$J$7:$J$21,0)),"") | N14: =IFERROR(INDEX($H$7:$H$21,MATCH(8,$J$7:$J$21,0)),"")
A15: 9 | F15: =IF(COUNT(C15:E15)<3,"",SUM(C15:E15)) | H15: =IF(OR(F15="",N(G15)=0),"",ROUND(F15/G15,2)) | I15: =IF(H15="","",COUNTIF($H$7:$H$21,">"&(H15+0.005))+1) | J15: =IF(I15="","",I15+COUNTIF($I$7:I15,I15)-1) | L15: =IFERROR(INDEX($I$7:$I$21,MATCH(9,$J$7:$J$21,0)),"") | M15: =IFERROR(INDEX($B$7:$B$21,MATCH(9,$J$7:$J$21,0)),"") | N15: =IFERROR(INDEX($H$7:$H$21,MATCH(9,$J$7:$J$21,0)),"")
A16: 10 | F16: =IF(COUNT(C16:E16)<3,"",SUM(C16:E16)) | H16: =IF(OR(F16="",N(G16)=0),"",ROUND(F16/G16,2)) | I16: =IF(H16="","",COUNTIF($H$7:$H$21,">"&(H16+0.005))+1) | J16: =IF(I16="","",I16+COUNTIF($I$7:I16,I16)-1) | L16: =IFERROR(INDEX($I$7:$I$21,MATCH(10,$J$7:$J$21,0)),"") | M16: =IFERROR(INDEX($B$7:$B$21,MATCH(10,$J$7:$J$21,0)),"") | N16: =IFERROR(INDEX($H$7:$H$21,MATCH(10,$J$7:$J$21,0)),"")
A17: 11 | F17: =IF(COUNT(C17:E17)<3,"",SUM(C17:E17)) | H17: =IF(OR(F17="",N(G17)=0),"",ROUND(F17/G17,2)) | I17: =IF(H17="","",COUNTIF($H$7:$H$21,">"&(H17+0.005))+1) | J17: =IF(I17="","",I17+COUNTIF($I$7:I17,I17)-1) | L17: =IFERROR(INDEX($I$7:$I$21,MATCH(11,$J$7:$J$21,0)),"") | M17: =IFERROR(INDEX($B$7:$B$21,MATCH(11,$J$7:$J$21,0)),"") | N17: =IFERROR(INDEX($H$7:$H$21,MATCH(11,$J$7:$J$21,0)),"")
A18: 12 | F18: =IF(COUNT(C18:E18)<3,"",SUM(C18:E18)) | H18: =IF(OR(F18="",N(G18)=0),"",ROUND(F18/G18,2)) | I18: =IF(H18="","",COUNTIF($H$7:$H$21,">"&(H18+0.005))+1) | J18: =IF(I18="","",I18+COUNTIF($I$7:I18,I18)-1) | L18: =IFERROR(INDEX($I$7:$I$21,MATCH(12,$J$7:$J$21,0)),"") | M18: =IFERROR(INDEX($B$7:$B$21,MATCH(12,$J$7:$J$21,0)),"") | N18: =IFERROR(INDEX($H$7:$H$21,MATCH(12,$J$7:$J$21,0)),"")
A19: 13 | F19: =IF(COUNT(C19:E19)<3,"",SUM(C19:E19)) | H19: =IF(OR(F19="",N(G19)=0),"",ROUND(F19/G19,2)) | I19: =IF(H19="","",COUNTIF($H$7:$H$21,">"&(H19+0.005))+1) | J19: =IF(I19="","",I19+COUNTIF($I$7:I19,I19)-1) | L19: =IFERROR(INDEX($I$7:$I$21,MATCH(13,$J$7:$J$21,0)),"") | M19: =IFERROR(INDEX($B$7:$B$21,MATCH(13,$J$7:$J$21,0)),"") | N19: =IFERROR(INDEX($H$7:$H$21,MATCH(13,$J$7:$J$21,0)),"")
A20: 14 | F20: =IF(COUNT(C20:E20)<3,"",SUM(C20:E20)) | H20: =IF(OR(F20="",N(G20)=0),"",ROUND(F20/G20,2)) | I20: =IF(H20="","",COUNTIF($H$7:$H$21,">"&(H20+0.005))+1) | J20: =IF(I20="","",I20+COUNTIF($I$7:I20,I20)-1) | L20: =IFERROR(INDEX($I$7:$I$21,MATCH(14,$J$7:$J$21,0)),"") | M20: =IFERROR(INDEX($B$7:$B$21,MATCH(14,$J$7:$J$21,0)),"") | N20: =IFERROR(INDEX($H$7:$H$21,MATCH(14,$J$7:$J$21,0)),"")
A21: 15 | F21: =IF(COUNT(C21:E21)<3,"",SUM(C21:E21)) | H21: =IF(OR(F21="",N(G21)=0),"",ROUND(F21/G21,2)) | I21: =IF(H21="","",COUNTIF($H$7:$H$21,">"&(H21+0.005))+1) | J21: =IF(I21="","",I21+COUNTIF($I$7:I21,I21)-1) | L21: =IFERROR(INDEX($I$7:$I$21,MATCH(15,$J$7:$J$21,0)),"") | M21: =IFERROR(INDEX($B$7:$B$21,MATCH(15,$J$7:$J$21,0)),"") | N21: =IFERROR(INDEX($H$7:$H$21,MATCH(15,$J$7:$J$21,0)),"")
B22: Smallest item = 1? | C22: =IF(COUNT(C7:C21)=0,"",IF(COUNTIF(C7:C21,1)=0,"✗ no 1",IF(COUNT(C7:C21)=COUNTIF(C7:C21,1)+COUNTIF(C7:C21,2)+COUNTIF(C7:C21,3)+COUNTIF(C7:C21,5)+COUNTIF(C7:C21,8)+COUNTIF(C7:C21,13)+COUNTIF(C7:C21,20),"✓","✗ scale"))) | D22: =IF(COUNT(D7:D21)=0,"",IF(COUNTIF(D7:D21,1)=0,"✗ no 1",IF(COUNT(D7:D21)=COUNTIF(D7:D21,1)+COUNTIF(D7:D21,2)+COUNTIF(D7:D21,3)+COUNTIF(D7:D21,5)+COUNTIF(D7:D21,8)+COUNTIF(D7:D21,13)+COUNTIF(D7:D21,20),"✓","✗ scale"))) | E22: =IF(COUNT(E7:E21)=0,"",IF(COUNTIF(E7:E21,1)=0,"✗ no 1",IF(COUNT(E7:E21)=COUNTIF(E7:E21,1)+COUNTIF(E7:E21,2)+COUNTIF(E7:E21,3)+COUNTIF(E7:E21,5)+COUNTIF(E7:E21,8)+COUNTIF(E7:E21,13)+COUNTIF(E7:E21,20),"✓","✗ scale"))) | G22: =IF(COUNT(G7:G21)=0,"",IF(COUNTIF(G7:G21,1)=0,"✗ no 1",IF(COUNT(G7:G21)=COUNTIF(G7:G21,1)+COUNTIF(G7:G21,2)+COUNTIF(G7:G21,3)+COUNTIF(G7:G21,5)+COUNTIF(G7:G21,8)+COUNTIF(G7:G21,13)+COUNTIF(G7:G21,20),"✓","✗ scale")))
B24: Modified Fibonacci scale: 1, 2, 3, 5, 8, 13, 20. Estimate ONE column at a time: the smallest item in the column gets a 1, everything else is sized against it.
B25: User-business value: how much users or the business gain. Time criticality: how fast the value decays, or whether a date is coming.
B26: Risk reduction / opportunity enablement: does doing it make other work safer, or possible?
B27: Job size stands in for duration. SAFe calls it a proxy: dependencies can override the order.
B28: Source: WSJF as defined by SAFe (Scaled Agile Framework).

Sheet Anchors
A1: Scoring anchors: agree these BEFORE anyone scores
A2: One session, one unit, one impact anchor, one evidence rule, for every item you will compare.
A4: Reach unit | B4: businesses / quarter | C4: People or events per time period. Every row uses this unit, or the scores are not comparable.
A6: Impact anchor question | C6: How much will this lift invoices paid on time, for each business it reaches?
A7: Impact scale
A8: massive | B8: 3
A9: high | B9: 2
A10: medium | B10: 1
A11: low | B11: 0.5
A12: minimal | B12: 0.25
A14: Confidence rule | C14: Adapted from the worked examples in Intercom's RICE article. Write the evidence next to the number.
A15: high | B15: 1 | C15: Data for reach, user research for impact, an engineering estimate for effort.
A16: medium | B16: 0.8 | C16: Data for reach and effort, but unsure about impact.
A17: low | B17: 0.5 | C17: Reach, impact and effort could all be off.
A18: below 50% | C18: "Total moonshot" (Intercom). Do not score it yet: run a cheap test first.
A20: Effort | B20: person-months | C20: Everyone involved. Whole numbers, and 0.5 for anything well under a month.
A22: Formula | B22: (R × I × C) ÷ E | C22: Total impact per time worked.
A24: Read the result
A25: • | C25: Sort, then re-evaluate: does any score look too high or too low? Check its inputs first.
A26: • | C26: Not a hard and fast rule: dependencies and table stakes can justify a different order.
A27: • | C27: RICE has no column for time (deadlines: see Cost of Delay) or for trust (guardrails).
A28: • | C28: Never compare RICE scores across teams or sessions: different units, anchors and habits.
A30: Source | C30: Sean McBride, "RICE: Simple prioritization for product managers", Intercom, 5 Jan 2018
C31: https://www.intercom.com/blog/rice-simple-prioritization-for-product-managers/
